scipy-stubs/__config__.pyi
scipy-stubs/__init__.pyi
scipy-stubs/_cyutility.pyi
scipy-stubs/_distributor_init.pyi
scipy-stubs/_lib/__init__.pyi
scipy-stubs/_lib/_array_api.pyi
scipy-stubs/_lib/_array_api_compat_vendor.pyi
scipy-stubs/_lib/_array_api_docs_tables.pyi
scipy-stubs/_lib/_array_api_no_0d.pyi
scipy-stubs/_lib/_array_api_override.pyi
scipy-stubs/_lib/_bunch.pyi
scipy-stubs/_lib/_ccallback.pyi
scipy-stubs/_lib/_ccallback_c.pyi
scipy-stubs/_lib/_disjoint_set.pyi
scipy-stubs/_lib/_docscrape.pyi
scipy-stubs/_lib/_elementwise_iterative_method.pyi
scipy-stubs/_lib/_gcutils.pyi
scipy-stubs/_lib/_pep440.pyi
scipy-stubs/_lib/_public_api.pyi
scipy-stubs/_lib/_sparse.pyi
scipy-stubs/_lib/_testutils.pyi
scipy-stubs/_lib/_tmpdirs.pyi
scipy-stubs/_lib/_uarray/__init__.pyi
scipy-stubs/_lib/_uarray/_backend.pyi
scipy-stubs/_lib/_util.pyi
scipy-stubs/_lib/deprecation.pyi
scipy-stubs/_lib/doccer.pyi
scipy-stubs/_lib/messagestream.pyi
scipy-stubs/_lib/uarray.pyi
scipy-stubs/_typing.pyi
scipy-stubs/cluster/__init__.pyi
scipy-stubs/cluster/_hierarchy.pyi
scipy-stubs/cluster/_optimal_leaf_ordering.pyi
scipy-stubs/cluster/_vq.pyi
scipy-stubs/cluster/hierarchy.pyi
scipy-stubs/cluster/vq.pyi
scipy-stubs/constants/__init__.pyi
scipy-stubs/constants/_codata.pyi
scipy-stubs/constants/_constants.pyi
scipy-stubs/constants/codata.pyi
scipy-stubs/constants/constants.pyi
scipy-stubs/datasets/__init__.pyi
scipy-stubs/datasets/_download_all.pyi
scipy-stubs/datasets/_fetchers.pyi
scipy-stubs/datasets/_registry.pyi
scipy-stubs/datasets/_typing.pyi
scipy-stubs/datasets/_utils.pyi
scipy-stubs/differentiate/__init__.pyi
scipy-stubs/differentiate/_differentiate.pyi
scipy-stubs/fft/__init__.pyi
scipy-stubs/fft/_backend.pyi
scipy-stubs/fft/_basic.pyi
scipy-stubs/fft/_basic_backend.pyi
scipy-stubs/fft/_debug_backends.pyi
scipy-stubs/fft/_fftlog.pyi
scipy-stubs/fft/_fftlog_backend.pyi
scipy-stubs/fft/_helper.pyi
scipy-stubs/fft/_realtransforms.pyi
scipy-stubs/fft/_realtransforms_backend.pyi
scipy_stubs-1.17.0.1.dist-info/licenses/LICENSE
scipy_stubs-1.17.0.1.dist-info/WHEEL
scipy_stubs-1.17.0.1.dist-info/METADATA
scipy_stubs-1.17.0.1.dist-info/RECORD
