Metadata-Version: 2.4
Name: scipy-stubs
Version: 1.17.0.1
Summary: Type annotations for SciPy
Keywords: scipy,typing,stubs,mypy,pyright,pep484,pep561,scipy-stubs
Author: Joren Hammudoglu
Author-email: Joren Hammudoglu <jhammudoglu@gmail.com>
License-Expression: BSD-3-Clause
License-File: LICENSE
Classifier: Development Status :: 5 - Production/Stable
Classifier: Intended Audience :: Developers
Classifier: Intended Audience :: Science/Research
Classifier: Operating System :: OS Independent
Classifier: Programming Language :: Python
Classifier: Programming Language :: Python :: 3
Classifier: Programming Language :: Python :: 3.11
Classifier: Programming Language :: Python :: 3.12
Classifier: Programming Language :: Python :: 3.13
Classifier: Programming Language :: Python :: 3.14
Classifier: Typing :: Stubs Only
Requires-Dist: optype[numpy]>=0.14.0,<0.16
Requires-Dist: scipy>=1.17.0,<1.18 ; extra == 'scipy'
Maintainer: Joren Hammudoglu, SciPy Developers
Maintainer-email: Joren Hammudoglu <jhammudoglu@gmail.com>, SciPy Developers <scipy-dev@python.org>
Requires-Python: >=3.11
Project-URL: Changelog, https://github.com/scipy/scipy-stubs/releases
Project-URL: Homepage, https://scipy.org/
Project-URL: Issues, https://github.com/scipy/scipy-stubs/issues
Project-URL: Repository, https://github.com/scipy/scipy-stubs
Provides-Extra: scipy
